compound_jsonapi/__init__.py
compound_jsonapi/fields.py
compound_jsonapi/schema.py
compound_jsonapi-1.0.1.dist-info/DESCRIPTION.rst
compound_jsonapi-1.0.1.dist-info/METADATA
compound_jsonapi-1.0.1.dist-info/RECORD
compound_jsonapi-1.0.1.dist-info/WHEEL
compound_jsonapi-1.0.1.dist-info/metadata.json
compound_jsonapi-1.0.1.dist-info/top_level.txt
