Metadata-Version: 2.0
Name: compound-jsonapi
Version: 1.0.1
Summary: Compound JSONAPI document extension for Marshmallow
Home-page: https://bitbucket.org/mhall/compound-jsonapi
Author: Mark Hall
Author-email: mark.hall@work.room3b.eu
License: UNKNOWN
Platform: UNKNOWN
Classifier: Programming Language :: Python
Requires-Dist: marshmallow (>=3.0.0b7)
